{
  "name": "practice",
  "permalink": "/docs/tags/practice",
  "docs": [
    {
      "id": "Examples/examples",
      "title": "Exercises",
      "description": "The goal is to explain Kubernetes and Docker Swarm topics in a practical way, like storage, deployments, services etc and provide exercises scenarios for everyone to follow along.",
      "permalink": "/docs/Examples/"
    },
    {
      "id": "Examples/k8s-configuration",
      "title": "Kubernetes Config Maps",
      "description": "[!NOTE]",
      "permalink": "/docs/Examples/k8s-configuration"
    },
    {
      "id": "Examples/k8s-deployments",
      "title": "Kubernetes Deployments",
      "description": "[!NOTE]",
      "permalink": "/docs/Examples/k8s-deployments"
    },
    {
      "id": "Fundamentals/kubernetes_intro",
      "title": "Kubernetes Introduction",
      "description": "Theory",
      "permalink": "/docs/Fundamentals/kubernetes_intro"
    },
    {
      "id": "Examples/k8s-jobs-cronjobs",
      "title": "Kubernetes Jobs",
      "description": "[!NOTE]",
      "permalink": "/docs/Examples/k8s-jobs-cronjobs"
    },
    {
      "id": "Examples/k8s-services",
      "title": "Kubernetes Services",
      "description": "This blog is a little bit longer than other parts of Kubernetes explained deep enough. Kubernetes networking is a very complex topic and trying to write about all nuances of different services and mechanisms would probably take a few blogs on it's own. Instead we will focus on specific areas of Kubernetes Networking: services and look at their practical applications.",
      "permalink": "/docs/Examples/k8s-services"
    },
    {
      "id": "Examples/k8s-storage-pv-pvc",
      "title": "Kubernetes Storage",
      "description": "[!NOTE]",
      "permalink": "/docs/Examples/k8s-storage-pv-pvc"
    },
    {
      "id": "Fundamentals/kubernetes",
      "title": "Practice Kubernetes",
      "description": "Overview",
      "permalink": "/docs/Fundamentals/kubernetes"
    }
  ],
  "allTagsPath": "/docs/tags"
}